paperstorage/__init__.py
paperstorage/__main__.py
paperstorage/paperstorage.py
paperstorage/tests/__init__.py
paperstorage/tests/test_generation.py
paperstorage/tests/test_restoration.py
paperstorage-0.9.9.dist-info/LICENSE
paperstorage-0.9.9.dist-info/METADATA
paperstorage-0.9.9.dist-info/WHEEL
paperstorage-0.9.9.dist-info/entry_points.txt
paperstorage-0.9.9.dist-info/top_level.txt
paperstorage-0.9.9.dist-info/RECORD
