Metadata-Version: 2.1
Name: paperstorage
Version: 0.9.9
Summary: A module to create paper backups for arbitrary data that are recoverable by simple means
Home-page: https://github.com/schroeding/paperstorage
Author: Florian Eder
Author-email: others.meder@gmail.com
License: UNKNOWN
Platform: UNKNOWN
Classifier: Development Status :: 4 - Beta
Classifier: Programming Language :: Python :: 3
Classifier: Intended Audience :: System Administrators
Classifier: Intended Audience :: End Users/Desktop
Classifier: Intended Audience :: Developers
Classifier: License :: OSI Approved :: Mozilla Public License 2.0 (MPL 2.0)
Classifier: Operating System :: OS Independent
Classifier: Topic :: System :: Archiving :: Backup
Classifier: Topic :: Printing
Requires-Python: >=3.6
Requires-Dist: qrcode (>=6.1)
Requires-Dist: reportlab (>=3.5)
Requires-Dist: six (>=1.15)
Requires-Dist: Pillow (>=8.1.0)
Requires-Dist: pyzbar (>=0.1.8)
Provides-Extra: full
Requires-Dist: pygame (~=2.0.0) ; extra == 'full'
